{
  "__AUTOGENERATED_FILE_DO_NOT_MODIFY_THIS_FILE_MANUALLY": "THERE_IS_NO_DATA_ONLY_ZUUL",
  "__INPUT_ARTIFACTS_HASH": {
    "io.quarkus.arc:arc": -946196139,
    "io.quarkus:quarkus-core": -1524809707,
    "io.quarkus:quarkus-core-deployment": 416491681,
    "org.junit.jupiter:junit-jupiter": -1032504578,
    "org.junit.platform:junit-platform-console-standalone": -1481831078,
    "org.junit.platform:junit-platform-launcher": -779382379,
    "repositories": -1949687017
  },
  "__RESOLVED_ARTIFACTS_HASH": {
    "io.github.dmlloyd:jdk-classfile-backport": 1460246868,
    "io.quarkus.arc:arc": -946614674,
    "io.quarkus.gizmo:gizmo": 1956106425,
    "io.quarkus.gizmo:gizmo2": -1887871201,
    "io.quarkus:quarkus-bootstrap-app-model": -923513404,
    "io.quarkus:quarkus-bootstrap-core": -343523199,
    "io.quarkus:quarkus-bootstrap-runner": -116121396,
    "io.quarkus:quarkus-builder": -17971146,
    "io.quarkus:quarkus-class-change-agent": -672019621,
    "io.quarkus:quarkus-classloader-commons": 400218834,
    "io.quarkus:quarkus-core": -369929068,
    "io.quarkus:quarkus-core-deployment": 2144211252,
    "io.quarkus:quarkus-development-mode-spi": 2069582730,
    "io.quarkus:quarkus-fs-util": 2100134833,
    "io.quarkus:quarkus-hibernate-validator-spi": -974025439,
    "io.quarkus:quarkus-ide-launcher": 1865115086,
    "io.smallrye.common:smallrye-common-annotation": -1541422257,
    "io.smallrye.common:smallrye-common-classloader": -805847306,
    "io.smallrye.common:smallrye-common-constraint": -1820281873,
    "io.smallrye.common:smallrye-common-cpu": -334932526,
    "io.smallrye.common:smallrye-common-expression": 368037826,
    "io.smallrye.common:smallrye-common-function": 1053549806,
    "io.smallrye.common:smallrye-common-io": 1446872542,
    "io.smallrye.common:smallrye-common-net": -1730731989,
    "io.smallrye.common:smallrye-common-os": 1149622573,
    "io.smallrye.common:smallrye-common-process": -457724872,
    "io.smallrye.common:smallrye-common-ref": 1084579247,
    "io.smallrye.common:smallrye-common-resource": -975318444,
    "io.smallrye.config:smallrye-config": -914261764,
    "io.smallrye.config:smallrye-config-common": -1066906865,
    "io.smallrye.config:smallrye-config-core": -365457456,
    "io.smallrye.reactive:mutiny": -1617211608,
    "io.smallrye:jandex": -359615195,
    "io.smallrye:jandex-gizmo2": -1995464502,
    "jakarta.annotation:jakarta.annotation-api": 196616042,
    "jakarta.el:jakarta.el-api": -78449182,
    "jakarta.enterprise:jakarta.enterprise.cdi-api": -289566630,
    "jakarta.enterprise:jakarta.enterprise.lang-model": 1858614948,
    "jakarta.inject:jakarta.inject-api": 188991469,
    "jakarta.interceptor:jakarta.interceptor-api": 71151213,
    "jakarta.json:jakarta.json-api": -1054410882,
    "jakarta.transaction:jakarta.transaction-api": -1232049293,
    "org.aesh:aesh": -684107909,
    "org.aesh:readline": 1066826701,
    "org.apache.commons:commons-lang3": -850748327,
    "org.apiguardian:apiguardian-api": 1279798469,
    "org.crac:crac": 853021667,
    "org.eclipse.microprofile.config:microprofile-config-api": 1033345756,
    "org.eclipse.parsson:parsson": 261021719,
    "org.eclipse.sisu:org.eclipse.sisu.inject": -1006980622,
    "org.fusesource.jansi:jansi": -1665988609,
    "org.graalvm.sdk:nativeimage": -1830909194,
    "org.graalvm.sdk:word": 921752333,
    "org.jboss.logging:commons-logging-jboss-logging": -1896182967,
    "org.jboss.logging:jboss-logging": -1889532189,
    "org.jboss.logmanager:jboss-logmanager": -1110999658,
    "org.jboss.slf4j:slf4j-jboss-logmanager": -1436669637,
    "org.jboss.threads:jboss-threads": -991353416,
    "org.jctools:jctools-core": 473448173,
    "org.jspecify:jspecify": 117231129,
    "org.junit.jupiter:junit-jupiter": -1180454764,
    "org.junit.jupiter:junit-jupiter-api": -452374709,
    "org.junit.jupiter:junit-jupiter-engine": 1758090696,
    "org.junit.jupiter:junit-jupiter-params": -1984293032,
    "org.junit.platform:junit-platform-commons": 880945443,
    "org.junit.platform:junit-platform-console-standalone": 690066095,
    "org.junit.platform:junit-platform-engine": -2133752461,
    "org.junit.platform:junit-platform-launcher": -1164782491,
    "org.opentest4j:opentest4j": -1711174392,
    "org.ow2.asm:asm": 611381606,
    "org.ow2.asm:asm-analysis": -254710036,
    "org.ow2.asm:asm-commons": 1032323649,
    "org.ow2.asm:asm-tree": -1593303232,
    "org.ow2.asm:asm-util": 610725920,
    "org.slf4j:slf4j-api": -1521593912,
    "org.wildfly.common:wildfly-common": 1915193746
  },
  "artifacts": {
    "io.github.dmlloyd:jdk-classfile-backport": {
      "shasums": {
        "jar": "34f5c9424d49bbfcc6277a28c3ac6da04520e8c6fcc49c59be7a2b1462ce5554"
      },
      "version": "24.0"
    },
    "io.quarkus.arc:arc": {
      "shasums": {
        "jar": "367cb0071dd9d09c371f806f3d0530a12b5ffeb7f285cda0de8c399559ef1b34"
      },
      "version": "3.27.3"
    },
    "io.quarkus.gizmo:gizmo": {
      "shasums": {
        "jar": "6d463d670ea45cb9a8241e99dd02c7e422d9982a2ff6e8623d338ac2a6c892b1"
      },
      "version": "1.9.0"
    },
    "io.quarkus.gizmo:gizmo2": {
      "shasums": {
        "jar": "bcb1ade9db85101dcd42cd81f5a0de2c15e50e696928957943723593ec719c70"
      },
      "version": "2.0.0.Beta6"
    },
    "io.quarkus:quarkus-bootstrap-app-model": {
      "shasums": {
        "jar": "6b14b184ea655f193a88b5f4669c1258743b7cdf0591c640986e46d0828969b2"
      },
      "version": "3.27.3"
    },
    "io.quarkus:quarkus-bootstrap-core": {
      "shasums": {
        "jar": "9915dfac2f331b49140a60b74cd57d5a421d22951676a7a2c22a3dc37bc1032d"
      },
      "version": "3.27.3"
    },
    "io.quarkus:quarkus-bootstrap-runner": {
      "shasums": {
        "jar": "78c6624086038638192ae262bf1769bc58b32a6d90ded85b896536c07408ce5c"
      },
      "version": "3.27.3"
    },
    "io.quarkus:quarkus-builder": {
      "shasums": {
        "jar": "98faace102e51108a7e91a611ed48fdcb865c0191dcb5fdb92e17ed931131c35"
      },
      "version": "3.27.3"
    },
    "io.quarkus:quarkus-class-change-agent": {
      "shasums": {
        "jar": "8b58582d2898386f5bd4ea4fd3fdac787b54a3826df237f622fecce0fbdcbe7e"
      },
      "version": "3.27.3"
    },
    "io.quarkus:quarkus-classloader-commons": {
      "shasums": {
        "jar": "4c8e897cd3dff151b9ed4d196a0b7e6b79dd650249e34d06503f5c878fc59334"
      },
      "version": "3.27.3"
    },
    "io.quarkus:quarkus-core": {
      "shasums": {
        "jar": "42ca682fd671eefcd700a5bec211d12b997d85ef19faac43d65cd822732b5888"
      },
      "version": "3.27.3"
    },
    "io.quarkus:quarkus-core-deployment": {
      "shasums": {
        "jar": "a9401f2699f490256083a2ec1140dfc3f036ae9eac1477118d9a2da1ec079ca9"
      },
      "version": "3.27.3"
    },
    "io.quarkus:quarkus-development-mode-spi": {
      "shasums": {
        "jar": "cd8b0c853d89a6bc287238696e22ab13a78533ecf75fc91a1630afe1486ebb10"
      },
      "version": "3.27.3"
    },
    "io.quarkus:quarkus-fs-util": {
      "shasums": {
        "jar": "515792e2c261e704b5c052be21fdaa9cc43aa5fd8588df53cf2edd071fd9ee26"
      },
      "version": "1.1.0"
    },
    "io.quarkus:quarkus-hibernate-validator-spi": {
      "shasums": {
        "jar": "5c492045efcc2a4c1d8de1662becab2822c7da3fbdedccdb77ca5fac302224bb"
      },
      "version": "3.27.3"
    },
    "io.quarkus:quarkus-ide-launcher": {
      "shasums": {
        "jar": "afd67053b3505b6e12708ddabb9fa45680e052780cc91e611cc90e62bb65bec9"
      },
      "version": "3.27.3"
    },
    "io.smallrye.common:smallrye-common-annotation": {
      "shasums": {
        "jar": "ad3eff15b46fbf81bbc95315144640774bde7817c2e75981230a1fe39eb7429a"
      },
      "version": "2.13.9"
    },
    "io.smallrye.common:smallrye-common-classloader": {
      "shasums": {
        "jar": "27b7498b4d26e9288689570f8a859b08806d59f44fa0a4db03e60dd51d4d7884"
      },
      "version": "2.13.9"
    },
    "io.smallrye.common:smallrye-common-constraint": {
      "shasums": {
        "jar": "c75d6fcecb867480106ed16607f03930788838c4fd959d11e05a916e5eae3a01"
      },
      "version": "2.13.9"
    },
    "io.smallrye.common:smallrye-common-cpu": {
      "shasums": {
        "jar": "7ecaf8b4f048afb8a732fd798be4de29a33d9e01b58adce90fa22dfcedb6ef7c"
      },
      "version": "2.13.9"
    },
    "io.smallrye.common:smallrye-common-expression": {
      "shasums": {
        "jar": "45f4f698e5f1daf239313616ede8faa0f1682dcb19b2ba6ae5750a6c1337d834"
      },
      "version": "2.13.9"
    },
    "io.smallrye.common:smallrye-common-function": {
      "shasums": {
        "jar": "7f1fdd06f9201b00420569dbda7f5fc8c16b8ebc9e9c688f372709834804e3ca"
      },
      "version": "2.13.9"
    },
    "io.smallrye.common:smallrye-common-io": {
      "shasums": {
        "jar": "6132512fa1c32ea63b9f0dacb5fb85f5d418f25b7087d88db6ed294560a888eb"
      },
      "version": "2.13.9"
    },
    "io.smallrye.common:smallrye-common-net": {
      "shasums": {
        "jar": "5825dbae884cb9cbde7a5e93025fd29caf3d0c4848a98b2fe049129e6b9587a7"
      },
      "version": "2.13.9"
    },
    "io.smallrye.common:smallrye-common-os": {
      "shasums": {
        "jar": "8de1846ca0674a299cd6c37f66914ce72569019b5706267aa3963ce68fd87b36"
      },
      "version": "2.13.9"
    },
    "io.smallrye.common:smallrye-common-process": {
      "shasums": {
        "jar": "5c9fae9b4e3cb8e84c8b211aacfd1919b3e2f5a6aaf9664f34e2b2fa5b386e17"
      },
      "version": "2.13.9"
    },
    "io.smallrye.common:smallrye-common-ref": {
      "shasums": {
        "jar": "72e147f76dc3a2d7aac9f18b812708390d1d8cf768ad32f556852068616575d7"
      },
      "version": "2.13.9"
    },
    "io.smallrye.common:smallrye-common-resource": {
      "shasums": {
        "jar": "9ba62b4cc6ae4cf2492966d19795cf3a150a4bcf8bc88d646b1d34b8c8019dc8"
      },
      "version": "2.13.9"
    },
    "io.smallrye.config:smallrye-config": {
      "shasums": {
        "jar": "ca8d6fb0b020d874b707f2c4a13d6492d62ea7fffa95fe03c040f553f77998f4"
      },
      "version": "3.13.4"
    },
    "io.smallrye.config:smallrye-config-common": {
      "shasums": {
        "jar": "fd3fb6f0609d2cb95d26119912165f89036120392ff79cabe0bc24cdb7acda51"
      },
      "version": "3.13.4"
    },
    "io.smallrye.config:smallrye-config-core": {
      "shasums": {
        "jar": "b2ac5384844bae798b40c57057f131eb72754fb68366fb092bda5d913ee4a35b"
      },
      "version": "3.13.4"
    },
    "io.smallrye.reactive:mutiny": {
      "shasums": {
        "jar": "7e3d1ac6016cfb1526d8e49abf48bb72bf752305e6cd7f5609f9d3f75e04bd90"
      },
      "version": "2.9.5"
    },
    "io.smallrye:jandex": {
      "shasums": {
        "jar": "6be417290a1d343dd27b45cbd12e273deb4af30a2df5cb9e4bad880fb63945b2"
      },
      "version": "3.4.0"
    },
    "io.smallrye:jandex-gizmo2": {
      "shasums": {
        "jar": "6df02b54b40fa1b8bb4e7b9f6856815a2242d2221760522ef975258b405d5c81"
      },
      "version": "3.4.0"
    },
    "jakarta.annotation:jakarta.annotation-api": {
      "shasums": {
        "jar": "b01f55552284cfb149411e64eabca75e942d26d2e1786b32914250e4330afaa2"
      },
      "version": "3.0.0"
    },
    "jakarta.el:jakarta.el-api": {
      "shasums": {
        "jar": "7e84b5bed49de32b79cc5e85d90b6f5adb1a953ac67283adbb41c1e297f9c605"
      },
      "version": "6.0.1"
    },
    "jakarta.enterprise:jakarta.enterprise.cdi-api": {
      "shasums": {
        "jar": "c42c808f17925129a0800f618febe050d966e181a4c7384c8a5e7a0283d68699"
      },
      "version": "4.1.0"
    },
    "jakarta.enterprise:jakarta.enterprise.lang-model": {
      "shasums": {
        "jar": "bb56f571f60d2862b2387d5468fe8f5540f8094727283ed991f89082708095ee"
      },
      "version": "4.1.0"
    },
    "jakarta.inject:jakarta.inject-api": {
      "shasums": {
        "jar": "f7dc98062fccf14126abb751b64fab12c312566e8cbdc8483598bffcea93af7c"
      },
      "version": "2.0.1"
    },
    "jakarta.interceptor:jakarta.interceptor-api": {
      "shasums": {
        "jar": "d240d72b4dd38a2e431c804079810010cb97903678fa5f987fb7434878b04398"
      },
      "version": "2.2.0"
    },
    "jakarta.json:jakarta.json-api": {
      "shasums": {
        "jar": "bc934142805ea1d794f1440563965a3861a2a9fb7414ecd3fe44f26500734414"
      },
      "version": "2.1.3"
    },
    "jakarta.transaction:jakarta.transaction-api": {
      "shasums": {
        "jar": "50c0a7c760c13ae6c042acf182b28f0047413db95b4636fb8879bcffab5ba875"
      },
      "version": "2.0.1"
    },
    "org.aesh:aesh": {
      "shasums": {
        "jar": "8c1e17fd1ab9d3a736bdee7fbd649e174f7dc26c1ceeac6e9ea596a9d63fcffd"
      },
      "version": "2.8.2"
    },
    "org.aesh:readline": {
      "shasums": {
        "jar": "601eb6cbc77a8b07b8014ba89cf3fbdda20fcdb96493e57466d3753fa26accde"
      },
      "version": "2.6"
    },
    "org.apache.commons:commons-lang3": {
      "shasums": {
        "jar": "4eeeae8d20c078abb64b015ec158add383ac581571cddc45c68f0c9ae0230720"
      },
      "version": "3.18.0"
    },
    "org.apiguardian:apiguardian-api": {
      "shasums": {
        "jar": "b509448ac506d607319f182537f0b35d71007582ec741832a1f111e5b5b70b38"
      },
      "version": "1.1.2"
    },
    "org.crac:crac": {
      "shasums": {
        "jar": "f4426e1641c8f0fa2f025a4cd7c40c285abaf265930e6717adfcaef03d034850"
      },
      "version": "1.5.0"
    },
    "org.eclipse.microprofile.config:microprofile-config-api": {
      "shasums": {
        "jar": "dee277f81e1edfeafd5e43589441ecdf434500fe4a31d035e74b8e6d8e7bfd91"
      },
      "version": "3.1"
    },
    "org.eclipse.parsson:parsson": {
      "shasums": {
        "jar": "c21db018f8ac6cf79893f1af77f1cd337937bd12ae6fa3d4b10f5a00819ee56c"
      },
      "version": "1.1.7"
    },
    "org.eclipse.sisu:org.eclipse.sisu.inject": {
      "shasums": {
        "jar": "1cbd7a965a5e2a9ea823bab311962a4e5aa5c240705bdbad5a52b40ffdfa1004"
      },
      "version": "0.9.0.M4"
    },
    "org.fusesource.jansi:jansi": {
      "shasums": {
        "jar": "6cd91991323dd7b2fb28ca93d7ac12af5a86a2f53279e2b35827b30313fd0b9f"
      },
      "version": "2.4.0"
    },
    "org.graalvm.sdk:nativeimage": {
      "shasums": {
        "jar": "b20c00823c194cadcafc8e853b96a5754e641b467dc56634e738d756b308ad9a"
      },
      "version": "23.1.2"
    },
    "org.graalvm.sdk:word": {
      "shasums": {
        "jar": "2ae7a71ff3f53f61d1d7360a6152f67ce3902ae86ca22b30b70208dc0cf4e039"
      },
      "version": "23.1.2"
    },
    "org.jboss.logging:commons-logging-jboss-logging": {
      "shasums": {
        "jar": "f12176263ea25f4e78bb4fa4b36d335a29738dde6a8123e1b6da89a655d150ff"
      },
      "version": "1.0.0.Final"
    },
    "org.jboss.logging:jboss-logging": {
      "shasums": {
        "jar": "5e08a4b092dc85b337f0910a740571d8720cfa565fabd880a8caf94a657ca416"
      },
      "version": "3.6.1.Final"
    },
    "org.jboss.logmanager:jboss-logmanager": {
      "shasums": {
        "jar": "c1e7de682a4871a8e4eefb26adaf0fcc63cd0913543c50aa6b7f46fa5ec151fe"
      },
      "version": "3.1.2.Final"
    },
    "org.jboss.slf4j:slf4j-jboss-logmanager": {
      "shasums": {
        "jar": "ba469a975e9d1e79f34a8baa1a0afa8b01bbd8cf080537c0e0899476d31db84b"
      },
      "version": "2.0.2.Final"
    },
    "org.jboss.threads:jboss-threads": {
      "shasums": {
        "jar": "d3af2f6b942eae683ff2de7dfe68467f8d570cbba8db37fe858977349c3bf2aa"
      },
      "version": "3.9.1"
    },
    "org.jctools:jctools-core": {
      "shasums": {
        "jar": "d65e5f38bcd0984e26f87187687f1f70dd52740c4d5e046f8d104e01ab5db95f"
      },
      "version": "4.0.5"
    },
    "org.jspecify:jspecify": {
      "shasums": {
        "jar": "1fad6e6be7557781e4d33729d49ae1cdc8fdda6fe477bb0cc68ce351eafdfbab"
      },
      "version": "1.0.0"
    },
    "org.junit.jupiter:junit-jupiter": {
      "shasums": {
        "jar": "784b65815f479a0c99a9d3a573b142e2a525efb6025d97f751b19e72f90aeda3"
      },
      "version": "6.0.3"
    },
    "org.junit.jupiter:junit-jupiter-api": {
      "shasums": {
        "jar": "d655d7e6f0c7ae07f10a2f3bbaaebb6d30e9b26204a068ad9e9b3950aa28792c"
      },
      "version": "6.0.3"
    },
    "org.junit.jupiter:junit-jupiter-engine": {
      "shasums": {
        "jar": "1e2fab61ad27ea08fc7c70dd9677cf8c6d1ae5434d42dcfdd633b12c7e7c04d0"
      },
      "version": "6.0.3"
    },
    "org.junit.jupiter:junit-jupiter-params": {
      "shasums": {
        "jar": "cf2947e2302b9f8c8a059259a277881c1cadae8fbc2514c16a925cfeb7beb2e5"
      },
      "version": "6.0.3"
    },
    "org.junit.platform:junit-platform-commons": {
      "shasums": {
        "jar": "39f262d09c3d52719fe0b77f080e90a3695e285d779a41b232e17963ae5da200"
      },
      "version": "6.0.3"
    },
    "org.junit.platform:junit-platform-console-standalone": {
      "shasums": {
        "jar": "3ba0d6150af79214a1411f9ea2fbef864eef68b68c89a17f672c0b89bff9d3a2"
      },
      "version": "6.0.3"
    },
    "org.junit.platform:junit-platform-engine": {
      "shasums": {
        "jar": "491e9e4f745f161b8a8e4186a1a7c6a450ea12c70930c9aedae427215301d947"
      },
      "version": "6.0.3"
    },
    "org.junit.platform:junit-platform-launcher": {
      "shasums": {
        "jar": "315608372e4dc44bca0ccb3ae8a07ecc206b3367033fa05748a03ccd563f1301"
      },
      "version": "6.0.3"
    },
    "org.opentest4j:opentest4j": {
      "shasums": {
        "jar": "48e2df636cab6563ced64dcdff8abb2355627cb236ef0bf37598682ddf742f1b"
      },
      "version": "1.3.0"
    },
    "org.ow2.asm:asm": {
      "shasums": {
        "jar": "876eab6a83daecad5ca67eb9fcabb063c97b5aeb8cf1fca7a989ecde17522051"
      },
      "version": "9.8"
    },
    "org.ow2.asm:asm-analysis": {
      "shasums": {
        "jar": "e640732fbcd3c6271925a504f125e38384688f4dfbbf92c8622dfcee0d09edb9"
      },
      "version": "9.8"
    },
    "org.ow2.asm:asm-commons": {
      "shasums": {
        "jar": "3301a1c1cb4c59fcc5292648dac1d7c5aed4c0f067dfbe88873b8cdfe77404f4"
      },
      "version": "9.8"
    },
    "org.ow2.asm:asm-tree": {
      "shasums": {
        "jar": "14b7880cb7c85eed101e2710432fc3ffb83275532a6a894dc4c4095d49ad59f1"
      },
      "version": "9.8"
    },
    "org.ow2.asm:asm-util": {
      "shasums": {
        "jar": "8ba0460ecb28fd0e2980e5f3ef3433a513a457bc077f81a53bdc75b587a08d15"
      },
      "version": "9.8"
    },
    "org.slf4j:slf4j-api": {
      "shasums": {
        "jar": "7b751d952061954d5abfed7181c1f645d336091b679891591d63329c622eb832"
      },
      "version": "2.0.17"
    },
    "org.wildfly.common:wildfly-common": {
      "shasums": {
        "jar": "fa4a710db7ae3e598a5f41639eb54e9f7b09de5fd0f58f56bd6070f21d956374"
      },
      "version": "2.0.1"
    }
  },
  "dependencies": {
    "io.quarkus.arc:arc": [
      "io.smallrye.reactive:mutiny",
      "jakarta.annotation:jakarta.annotation-api",
      "jakarta.enterprise:jakarta.enterprise.cdi-api",
      "jakarta.transaction:jakarta.transaction-api",
      "org.jboss.logging:jboss-logging"
    ],
    "io.quarkus.gizmo:gizmo": [
      "io.smallrye:jandex",
      "org.ow2.asm:asm",
      "org.ow2.asm:asm-util"
    ],
    "io.quarkus.gizmo:gizmo2": [
      "io.github.dmlloyd:jdk-classfile-backport",
      "io.smallrye.common:smallrye-common-constraint",
      "io.smallrye.common:smallrye-common-resource"
    ],
    "io.quarkus:quarkus-bootstrap-app-model": [
      "io.quarkus:quarkus-fs-util",
      "org.jboss.logging:commons-logging-jboss-logging",
      "org.jboss.logging:jboss-logging"
    ],
    "io.quarkus:quarkus-bootstrap-core": [
      "io.quarkus:quarkus-bootstrap-app-model",
      "io.quarkus:quarkus-classloader-commons",
      "io.smallrye.common:smallrye-common-io"
    ],
    "io.quarkus:quarkus-bootstrap-runner": [
      "io.quarkus:quarkus-classloader-commons",
      "io.smallrye.common:smallrye-common-io",
      "org.crac:crac",
      "org.jboss.logging:jboss-logging",
      "org.jboss.logmanager:jboss-logmanager"
    ],
    "io.quarkus:quarkus-builder": [
      "io.smallrye.common:smallrye-common-constraint",
      "org.jboss.logging:jboss-logging",
      "org.jboss.threads:jboss-threads",
      "org.wildfly.common:wildfly-common"
    ],
    "io.quarkus:quarkus-core": [
      "io.quarkus:quarkus-bootstrap-runner",
      "io.quarkus:quarkus-development-mode-spi",
      "io.quarkus:quarkus-fs-util",
      "io.quarkus:quarkus-ide-launcher",
      "io.smallrye.common:smallrye-common-os",
      "io.smallrye.config:smallrye-config",
      "jakarta.annotation:jakarta.annotation-api",
      "jakarta.enterprise:jakarta.enterprise.cdi-api",
      "jakarta.inject:jakarta.inject-api",
      "org.jboss.logging:jboss-logging",
      "org.jboss.logmanager:jboss-logmanager",
      "org.jboss.slf4j:slf4j-jboss-logmanager",
      "org.jboss.threads:jboss-threads",
      "org.slf4j:slf4j-api",
      "org.wildfly.common:wildfly-common"
    ],
    "io.quarkus:quarkus-core-deployment": [
      "io.quarkus.gizmo:gizmo",
      "io.quarkus.gizmo:gizmo2",
      "io.quarkus:quarkus-bootstrap-core",
      "io.quarkus:quarkus-builder",
      "io.quarkus:quarkus-class-change-agent",
      "io.quarkus:quarkus-classloader-commons",
      "io.quarkus:quarkus-core",
      "io.quarkus:quarkus-development-mode-spi",
      "io.quarkus:quarkus-hibernate-validator-spi",
      "io.smallrye.common:smallrye-common-os",
      "io.smallrye.common:smallrye-common-process",
      "io.smallrye:jandex",
      "io.smallrye:jandex-gizmo2",
      "org.aesh:aesh",
      "org.aesh:readline",
      "org.apache.commons:commons-lang3",
      "org.eclipse.sisu:org.eclipse.sisu.inject",
      "org.graalvm.sdk:nativeimage",
      "org.junit.jupiter:junit-jupiter",
      "org.junit.platform:junit-platform-launcher",
      "org.ow2.asm:asm",
      "org.ow2.asm:asm-commons",
      "org.wildfly.common:wildfly-common"
    ],
    "io.quarkus:quarkus-development-mode-spi": [
      "org.jboss.logging:jboss-logging"
    ],
    "io.quarkus:quarkus-hibernate-validator-spi": [
      "io.quarkus:quarkus-builder",
      "io.smallrye:jandex"
    ],
    "io.smallrye.common:smallrye-common-constraint": [
      "org.jboss.logging:jboss-logging"
    ],
    "io.smallrye.common:smallrye-common-expression": [
      "io.smallrye.common:smallrye-common-function",
      "org.jboss.logging:jboss-logging"
    ],
    "io.smallrye.common:smallrye-common-function": [
      "io.smallrye.common:smallrye-common-constraint",
      "org.jboss.logging:jboss-logging"
    ],
    "io.smallrye.common:smallrye-common-net": [
      "io.smallrye.common:smallrye-common-constraint",
      "org.jboss.logging:jboss-logging"
    ],
    "io.smallrye.common:smallrye-common-process": [
      "io.smallrye.common:smallrye-common-function",
      "io.smallrye.common:smallrye-common-os",
      "org.jboss.logging:jboss-logging"
    ],
    "io.smallrye.common:smallrye-common-ref": [
      "io.smallrye.common:smallrye-common-constraint"
    ],
    "io.smallrye.common:smallrye-common-resource": [
      "io.smallrye.common:smallrye-common-constraint"
    ],
    "io.smallrye.config:smallrye-config": [
      "io.smallrye.config:smallrye-config-core",
      "org.jboss.logging:jboss-logging"
    ],
    "io.smallrye.config:smallrye-config-common": [
      "io.smallrye.common:smallrye-common-classloader",
      "org.eclipse.microprofile.config:microprofile-config-api",
      "org.jboss.logging:jboss-logging"
    ],
    "io.smallrye.config:smallrye-config-core": [
      "io.smallrye.common:smallrye-common-annotation",
      "io.smallrye.common:smallrye-common-classloader",
      "io.smallrye.common:smallrye-common-constraint",
      "io.smallrye.common:smallrye-common-expression",
      "io.smallrye.config:smallrye-config-common",
      "jakarta.annotation:jakarta.annotation-api",
      "org.eclipse.microprofile.config:microprofile-config-api",
      "org.jboss.logging:jboss-logging"
    ],
    "io.smallrye.reactive:mutiny": [
      "io.smallrye.common:smallrye-common-annotation",
      "org.jctools:jctools-core"
    ],
    "io.smallrye:jandex-gizmo2": [
      "io.quarkus.gizmo:gizmo2",
      "io.smallrye:jandex"
    ],
    "jakarta.enterprise:jakarta.enterprise.cdi-api": [
      "jakarta.annotation:jakarta.annotation-api",
      "jakarta.el:jakarta.el-api",
      "jakarta.enterprise:jakarta.enterprise.lang-model",
      "jakarta.inject:jakarta.inject-api",
      "jakarta.interceptor:jakarta.interceptor-api"
    ],
    "org.aesh:aesh": [
      "org.aesh:readline"
    ],
    "org.aesh:readline": [
      "org.fusesource.jansi:jansi"
    ],
    "org.eclipse.parsson:parsson": [
      "jakarta.json:jakarta.json-api"
    ],
    "org.eclipse.sisu:org.eclipse.sisu.inject": [
      "org.ow2.asm:asm"
    ],
    "org.graalvm.sdk:nativeimage": [
      "org.graalvm.sdk:word"
    ],
    "org.jboss.logging:commons-logging-jboss-logging": [
      "org.jboss.logging:jboss-logging"
    ],
    "org.jboss.logmanager:jboss-logmanager": [
      "io.smallrye.common:smallrye-common-constraint",
      "io.smallrye.common:smallrye-common-cpu",
      "io.smallrye.common:smallrye-common-expression",
      "io.smallrye.common:smallrye-common-net",
      "io.smallrye.common:smallrye-common-os",
      "io.smallrye.common:smallrye-common-ref",
      "jakarta.json:jakarta.json-api",
      "org.eclipse.parsson:parsson",
      "org.jboss.logging:jboss-logging"
    ],
    "org.jboss.threads:jboss-threads": [
      "io.smallrye.common:smallrye-common-annotation",
      "io.smallrye.common:smallrye-common-constraint",
      "io.smallrye.common:smallrye-common-cpu",
      "io.smallrye.common:smallrye-common-function",
      "org.jboss.logging:jboss-logging",
      "org.wildfly.common:wildfly-common"
    ],
    "org.junit.jupiter:junit-jupiter": [
      "org.junit.jupiter:junit-jupiter-api",
      "org.junit.jupiter:junit-jupiter-engine",
      "org.junit.jupiter:junit-jupiter-params"
    ],
    "org.junit.jupiter:junit-jupiter-api": [
      "org.apiguardian:apiguardian-api",
      "org.jspecify:jspecify",
      "org.junit.platform:junit-platform-commons",
      "org.opentest4j:opentest4j"
    ],
    "org.junit.jupiter:junit-jupiter-engine": [
      "org.apiguardian:apiguardian-api",
      "org.jspecify:jspecify",
      "org.junit.jupiter:junit-jupiter-api",
      "org.junit.platform:junit-platform-engine"
    ],
    "org.junit.jupiter:junit-jupiter-params": [
      "org.apiguardian:apiguardian-api",
      "org.jspecify:jspecify",
      "org.junit.jupiter:junit-jupiter-api"
    ],
    "org.junit.platform:junit-platform-commons": [
      "org.apiguardian:apiguardian-api",
      "org.jspecify:jspecify"
    ],
    "org.junit.platform:junit-platform-engine": [
      "org.apiguardian:apiguardian-api",
      "org.jspecify:jspecify",
      "org.junit.platform:junit-platform-commons",
      "org.opentest4j:opentest4j"
    ],
    "org.junit.platform:junit-platform-launcher": [
      "org.apiguardian:apiguardian-api",
      "org.jspecify:jspecify",
      "org.junit.platform:junit-platform-engine"
    ],
    "org.ow2.asm:asm-analysis": [
      "org.ow2.asm:asm-tree"
    ],
    "org.ow2.asm:asm-commons": [
      "org.ow2.asm:asm",
      "org.ow2.asm:asm-tree"
    ],
    "org.ow2.asm:asm-tree": [
      "org.ow2.asm:asm"
    ],
    "org.ow2.asm:asm-util": [
      "org.ow2.asm:asm",
      "org.ow2.asm:asm-analysis",
      "org.ow2.asm:asm-tree"
    ],
    "org.wildfly.common:wildfly-common": [
      "io.smallrye.common:smallrye-common-cpu",
      "io.smallrye.common:smallrye-common-expression",
      "io.smallrye.common:smallrye-common-net",
      "io.smallrye.common:smallrye-common-os",
      "io.smallrye.common:smallrye-common-ref"
    ]
  },
  "packages": {
    "io.github.dmlloyd:jdk-classfile-backport": [
      "io.github.dmlloyd.classfile",
      "io.github.dmlloyd.classfile.attribute",
      "io.github.dmlloyd.classfile.components",
      "io.github.dmlloyd.classfile.constantpool",
      "io.github.dmlloyd.classfile.extras",
      "io.github.dmlloyd.classfile.extras.constant",
      "io.github.dmlloyd.classfile.extras.reflect",
      "io.github.dmlloyd.classfile.impl",
      "io.github.dmlloyd.classfile.impl.verifier",
      "io.github.dmlloyd.classfile.instruction"
    ],
    "io.quarkus.arc:arc": [
      "io.quarkus.arc",
      "io.quarkus.arc.impl",
      "io.quarkus.arc.impl.bcextensions"
    ],
    "io.quarkus.gizmo:gizmo": [
      "io.quarkus.gizmo"
    ],
    "io.quarkus.gizmo:gizmo2": [
      "io.quarkus.gizmo2",
      "io.quarkus.gizmo2.creator",
      "io.quarkus.gizmo2.creator.ops",
      "io.quarkus.gizmo2.desc",
      "io.quarkus.gizmo2.impl",
      "io.quarkus.gizmo2.impl.constant"
    ],
    "io.quarkus:quarkus-bootstrap-app-model": [
      "io.quarkus.bootstrap",
      "io.quarkus.bootstrap.model",
      "io.quarkus.bootstrap.model.gradle",
      "io.quarkus.bootstrap.model.gradle.impl",
      "io.quarkus.bootstrap.resolver",
      "io.quarkus.bootstrap.util",
      "io.quarkus.bootstrap.workspace",
      "io.quarkus.maven",
      "io.quarkus.maven.dependency",
      "io.quarkus.paths",
      "io.quarkus.sbom",
      "io.quarkus.util"
    ],
    "io.quarkus:quarkus-bootstrap-core": [
      "io.quarkus.bootstrap",
      "io.quarkus.bootstrap.app",
      "io.quarkus.bootstrap.classloading",
      "io.quarkus.bootstrap.devmode",
      "io.quarkus.bootstrap.jbang",
      "io.quarkus.bootstrap.prebuild",
      "io.quarkus.bootstrap.utils"
    ],
    "io.quarkus:quarkus-bootstrap-runner": [
      "io.quarkus.bootstrap.forkjoin",
      "io.quarkus.bootstrap.graal",
      "io.quarkus.bootstrap.logging",
      "io.quarkus.bootstrap.naming",
      "io.quarkus.bootstrap.runner"
    ],
    "io.quarkus:quarkus-builder": [
      "io.quarkus.builder",
      "io.quarkus.builder.diag",
      "io.quarkus.builder.item",
      "io.quarkus.builder.json",
      "io.quarkus.builder.location"
    ],
    "io.quarkus:quarkus-class-change-agent": [
      "io.quarkus.changeagent"
    ],
    "io.quarkus:quarkus-classloader-commons": [
      "io.quarkus.commons.classloading"
    ],
    "io.quarkus:quarkus-core": [
      "io.quarkus",
      "io.quarkus.devservice.runtime.config",
      "io.quarkus.devservices.crossclassloader.runtime",
      "io.quarkus.logging",
      "io.quarkus.runtime",
      "io.quarkus.runtime.annotations",
      "io.quarkus.runtime.configuration",
      "io.quarkus.runtime.console",
      "io.quarkus.runtime.dev.io",
      "io.quarkus.runtime.graal",
      "io.quarkus.runtime.init",
      "io.quarkus.runtime.logging",
      "io.quarkus.runtime.metrics",
      "io.quarkus.runtime.recording.substitutions",
      "io.quarkus.runtime.rest",
      "io.quarkus.runtime.shutdown",
      "io.quarkus.runtime.ssl",
      "io.quarkus.runtime.test",
      "io.quarkus.runtime.types",
      "io.quarkus.runtime.util"
    ],
    "io.quarkus:quarkus-core-deployment": [
      "io.quarkus.banner",
      "io.quarkus.deployment",
      "io.quarkus.deployment.annotations",
      "io.quarkus.deployment.bean",
      "io.quarkus.deployment.builditem",
      "io.quarkus.deployment.builditem.nativeimage",
      "io.quarkus.deployment.cmd",
      "io.quarkus.deployment.codegen",
      "io.quarkus.deployment.configuration",
      "io.quarkus.deployment.configuration.matching",
      "io.quarkus.deployment.configuration.tracker",
      "io.quarkus.deployment.console",
      "io.quarkus.deployment.dev",
      "io.quarkus.deployment.dev.devservices",
      "io.quarkus.deployment.dev.filesystem",
      "io.quarkus.deployment.dev.filesystem.watch",
      "io.quarkus.deployment.dev.io",
      "io.quarkus.deployment.dev.remote",
      "io.quarkus.deployment.dev.testing",
      "io.quarkus.deployment.execannotations",
      "io.quarkus.deployment.ide",
      "io.quarkus.deployment.images",
      "io.quarkus.deployment.index",
      "io.quarkus.deployment.jbang",
      "io.quarkus.deployment.logging",
      "io.quarkus.deployment.metrics",
      "io.quarkus.deployment.mutability",
      "io.quarkus.deployment.naming",
      "io.quarkus.deployment.pkg",
      "io.quarkus.deployment.pkg.builditem",
      "io.quarkus.deployment.pkg.steps",
      "io.quarkus.deployment.proxy",
      "io.quarkus.deployment.recording",
      "io.quarkus.deployment.recording.substitutions",
      "io.quarkus.deployment.sbom",
      "io.quarkus.deployment.shutdown",
      "io.quarkus.deployment.steps",
      "io.quarkus.deployment.types",
      "io.quarkus.deployment.util",
      "io.quarkus.runner.bootstrap"
    ],
    "io.quarkus:quarkus-development-mode-spi": [
      "io.quarkus.dev",
      "io.quarkus.dev.appstate",
      "io.quarkus.dev.config",
      "io.quarkus.dev.console",
      "io.quarkus.dev.io",
      "io.quarkus.dev.spi",
      "io.quarkus.dev.testing",
      "io.quarkus.dev.testing.results"
    ],
    "io.quarkus:quarkus-fs-util": [
      "io.quarkus.fs.util",
      "io.quarkus.fs.util.base",
      "io.quarkus.fs.util.sysfs"
    ],
    "io.quarkus:quarkus-hibernate-validator-spi": [
      "io.quarkus.hibernate.validator.spi"
    ],
    "io.quarkus:quarkus-ide-launcher": [
      "io.quarkus.launcher"
    ],
    "io.smallrye.common:smallrye-common-annotation": [
      "io.smallrye.common.annotation"
    ],
    "io.smallrye.common:smallrye-common-classloader": [
      "io.smallrye.common.classloader"
    ],
    "io.smallrye.common:smallrye-common-constraint": [
      "io.smallrye.common.constraint"
    ],
    "io.smallrye.common:smallrye-common-cpu": [
      "io.smallrye.common.cpu"
    ],
    "io.smallrye.common:smallrye-common-expression": [
      "io.smallrye.common.expression"
    ],
    "io.smallrye.common:smallrye-common-function": [
      "io.smallrye.common.function"
    ],
    "io.smallrye.common:smallrye-common-io": [
      "io.smallrye.common.io.jar"
    ],
    "io.smallrye.common:smallrye-common-net": [
      "io.smallrye.common.net"
    ],
    "io.smallrye.common:smallrye-common-os": [
      "io.smallrye.common.os"
    ],
    "io.smallrye.common:smallrye-common-process": [
      "io.smallrye.common.process"
    ],
    "io.smallrye.common:smallrye-common-ref": [
      "io.smallrye.common.ref"
    ],
    "io.smallrye.common:smallrye-common-resource": [
      "io.smallrye.common.resource"
    ],
    "io.smallrye.config:smallrye-config": [
      "io.smallrye.config.inject"
    ],
    "io.smallrye.config:smallrye-config-common": [
      "io.smallrye.config.common",
      "io.smallrye.config.common.utils"
    ],
    "io.smallrye.config:smallrye-config-core": [
      "io.smallrye.config",
      "io.smallrye.config._private"
    ],
    "io.smallrye.reactive:mutiny": [
      "io.smallrye.mutiny",
      "io.smallrye.mutiny.converters",
      "io.smallrye.mutiny.converters.multi",
      "io.smallrye.mutiny.converters.uni",
      "io.smallrye.mutiny.groups",
      "io.smallrye.mutiny.helpers",
      "io.smallrye.mutiny.helpers.queues",
      "io.smallrye.mutiny.helpers.spies",
      "io.smallrye.mutiny.helpers.test",
      "io.smallrye.mutiny.infrastructure",
      "io.smallrye.mutiny.operators",
      "io.smallrye.mutiny.operators.multi",
      "io.smallrye.mutiny.operators.multi.builders",
      "io.smallrye.mutiny.operators.multi.multicast",
      "io.smallrye.mutiny.operators.multi.overflow",
      "io.smallrye.mutiny.operators.multi.processors",
      "io.smallrye.mutiny.operators.multi.replay",
      "io.smallrye.mutiny.operators.multi.split",
      "io.smallrye.mutiny.operators.uni",
      "io.smallrye.mutiny.operators.uni.builders",
      "io.smallrye.mutiny.subscription",
      "io.smallrye.mutiny.tuples",
      "io.smallrye.mutiny.unchecked"
    ],
    "io.smallrye:jandex": [
      "org.jboss.jandex"
    ],
    "io.smallrye:jandex-gizmo2": [
      "org.jboss.jandex.gizmo2"
    ],
    "jakarta.annotation:jakarta.annotation-api": [
      "jakarta.annotation",
      "jakarta.annotation.security",
      "jakarta.annotation.sql"
    ],
    "jakarta.el:jakarta.el-api": [
      "jakarta.el"
    ],
    "jakarta.enterprise:jakarta.enterprise.cdi-api": [
      "jakarta.decorator",
      "jakarta.enterprise.context",
      "jakarta.enterprise.context.control",
      "jakarta.enterprise.context.spi",
      "jakarta.enterprise.event",
      "jakarta.enterprise.inject",
      "jakarta.enterprise.inject.build.compatible.spi",
      "jakarta.enterprise.inject.literal",
      "jakarta.enterprise.inject.se",
      "jakarta.enterprise.inject.spi",
      "jakarta.enterprise.inject.spi.configurator",
      "jakarta.enterprise.invoke",
      "jakarta.enterprise.util"
    ],
    "jakarta.enterprise:jakarta.enterprise.lang-model": [
      "jakarta.enterprise.lang.model",
      "jakarta.enterprise.lang.model.declarations",
      "jakarta.enterprise.lang.model.types"
    ],
    "jakarta.inject:jakarta.inject-api": [
      "jakarta.inject"
    ],
    "jakarta.interceptor:jakarta.interceptor-api": [
      "jakarta.interceptor"
    ],
    "jakarta.json:jakarta.json-api": [
      "jakarta.json",
      "jakarta.json.spi",
      "jakarta.json.stream"
    ],
    "jakarta.transaction:jakarta.transaction-api": [
      "jakarta.transaction"
    ],
    "org.aesh:aesh": [
      "org.aesh",
      "org.aesh.command",
      "org.aesh.command.activator",
      "org.aesh.command.alias",
      "org.aesh.command.builder",
      "org.aesh.command.completer",
      "org.aesh.command.container",
      "org.aesh.command.converter",
      "org.aesh.command.export",
      "org.aesh.command.impl",
      "org.aesh.command.impl.activator",
      "org.aesh.command.impl.completer",
      "org.aesh.command.impl.container",
      "org.aesh.command.impl.converter",
      "org.aesh.command.impl.internal",
      "org.aesh.command.impl.invocation",
      "org.aesh.command.impl.operator",
      "org.aesh.command.impl.parser",
      "org.aesh.command.impl.populator",
      "org.aesh.command.impl.registry",
      "org.aesh.command.impl.renderer",
      "org.aesh.command.impl.result",
      "org.aesh.command.impl.shell",
      "org.aesh.command.impl.validator",
      "org.aesh.command.invocation",
      "org.aesh.command.man",
      "org.aesh.command.man.parser",
      "org.aesh.command.map",
      "org.aesh.command.operator",
      "org.aesh.command.option",
      "org.aesh.command.parser",
      "org.aesh.command.populator",
      "org.aesh.command.registry",
      "org.aesh.command.renderer",
      "org.aesh.command.result",
      "org.aesh.command.settings",
      "org.aesh.command.shell",
      "org.aesh.command.validator",
      "org.aesh.comparators",
      "org.aesh.complete",
      "org.aesh.constants",
      "org.aesh.converter",
      "org.aesh.graphics",
      "org.aesh.impl.util",
      "org.aesh.io",
      "org.aesh.io.filter",
      "org.aesh.io.scanner",
      "org.aesh.parser",
      "org.aesh.readline",
      "org.aesh.selector",
      "org.aesh.util",
      "org.aesh.util.completer",
      "org.aesh.util.graal"
    ],
    "org.aesh:readline": [
      "org.aesh.readline",
      "org.aesh.readline.action",
      "org.aesh.readline.action.mappings",
      "org.aesh.readline.alias",
      "org.aesh.readline.completion",
      "org.aesh.readline.cursor",
      "org.aesh.readline.editing",
      "org.aesh.readline.history",
      "org.aesh.readline.paste",
      "org.aesh.readline.terminal",
      "org.aesh.readline.terminal.formatting",
      "org.aesh.readline.terminal.impl",
      "org.aesh.readline.terminal.utils",
      "org.aesh.readline.tty.terminal",
      "org.aesh.readline.undo",
      "org.aesh.readline.util",
      "org.aesh.terminal",
      "org.aesh.terminal.io",
      "org.aesh.terminal.tty",
      "org.aesh.terminal.utils"
    ],
    "org.apache.commons:commons-lang3": [
      "org.apache.commons.lang3",
      "org.apache.commons.lang3.arch",
      "org.apache.commons.lang3.builder",
      "org.apache.commons.lang3.compare",
      "org.apache.commons.lang3.concurrent",
      "org.apache.commons.lang3.concurrent.locks",
      "org.apache.commons.lang3.event",
      "org.apache.commons.lang3.exception",
      "org.apache.commons.lang3.function",
      "org.apache.commons.lang3.math",
      "org.apache.commons.lang3.mutable",
      "org.apache.commons.lang3.reflect",
      "org.apache.commons.lang3.stream",
      "org.apache.commons.lang3.text",
      "org.apache.commons.lang3.text.translate",
      "org.apache.commons.lang3.time",
      "org.apache.commons.lang3.tuple",
      "org.apache.commons.lang3.util"
    ],
    "org.apiguardian:apiguardian-api": [
      "org.apiguardian.api"
    ],
    "org.crac:crac": [
      "org.crac",
      "org.crac.management"
    ],
    "org.eclipse.microprofile.config:microprofile-config-api": [
      "org.eclipse.microprofile.config",
      "org.eclipse.microprofile.config.inject",
      "org.eclipse.microprofile.config.spi"
    ],
    "org.eclipse.parsson:parsson": [
      "org.eclipse.parsson",
      "org.eclipse.parsson.api"
    ],
    "org.eclipse.sisu:org.eclipse.sisu.inject": [
      "org.eclipse.sisu",
      "org.eclipse.sisu.bean",
      "org.eclipse.sisu.inject",
      "org.eclipse.sisu.launch",
      "org.eclipse.sisu.osgi",
      "org.eclipse.sisu.space",
      "org.eclipse.sisu.wire",
      "org.sonatype.inject"
    ],
    "org.fusesource.jansi:jansi": [
      "org.fusesource.jansi",
      "org.fusesource.jansi.internal",
      "org.fusesource.jansi.io"
    ],
    "org.graalvm.sdk:nativeimage": [
      "com.oracle.svm.core.annotate",
      "org.graalvm.nativeimage",
      "org.graalvm.nativeimage.c",
      "org.graalvm.nativeimage.c.constant",
      "org.graalvm.nativeimage.c.function",
      "org.graalvm.nativeimage.c.struct",
      "org.graalvm.nativeimage.c.type",
      "org.graalvm.nativeimage.hosted",
      "org.graalvm.nativeimage.impl",
      "org.graalvm.nativeimage.impl.clinit"
    ],
    "org.graalvm.sdk:word": [
      "org.graalvm.word",
      "org.graalvm.word.impl"
    ],
    "org.jboss.logging:commons-logging-jboss-logging": [
      "org.apache.commons.logging",
      "org.apache.commons.logging.impl"
    ],
    "org.jboss.logging:jboss-logging": [
      "org.jboss.logging"
    ],
    "org.jboss.logmanager:jboss-logmanager": [
      "org.jboss.logmanager",
      "org.jboss.logmanager.configuration",
      "org.jboss.logmanager.configuration.filters",
      "org.jboss.logmanager.errormanager",
      "org.jboss.logmanager.filters",
      "org.jboss.logmanager.formatters",
      "org.jboss.logmanager.handlers"
    ],
    "org.jboss.slf4j:slf4j-jboss-logmanager": [
      "org.slf4j.impl"
    ],
    "org.jboss.threads:jboss-threads": [
      "org.jboss.threads",
      "org.jboss.threads.management"
    ],
    "org.jctools:jctools-core": [
      "org.jctools.counters",
      "org.jctools.maps",
      "org.jctools.queues",
      "org.jctools.queues.atomic",
      "org.jctools.queues.atomic.unpadded",
      "org.jctools.queues.unpadded",
      "org.jctools.util"
    ],
    "org.jspecify:jspecify": [
      "org.jspecify.annotations"
    ],
    "org.junit.jupiter:junit-jupiter-api": [
      "org.junit.jupiter.api",
      "org.junit.jupiter.api.condition",
      "org.junit.jupiter.api.extension",
      "org.junit.jupiter.api.extension.support",
      "org.junit.jupiter.api.function",
      "org.junit.jupiter.api.io",
      "org.junit.jupiter.api.parallel",
      "org.junit.jupiter.api.util"
    ],
    "org.junit.jupiter:junit-jupiter-engine": [
      "org.junit.jupiter.engine",
      "org.junit.jupiter.engine.config",
      "org.junit.jupiter.engine.descriptor",
      "org.junit.jupiter.engine.discovery",
      "org.junit.jupiter.engine.discovery.predicates",
      "org.junit.jupiter.engine.execution",
      "org.junit.jupiter.engine.extension",
      "org.junit.jupiter.engine.support"
    ],
    "org.junit.jupiter:junit-jupiter-params": [
      "org.junit.jupiter.params",
      "org.junit.jupiter.params.aggregator",
      "org.junit.jupiter.params.converter",
      "org.junit.jupiter.params.provider",
      "org.junit.jupiter.params.shadow.de.siegmar.fastcsv.reader",
      "org.junit.jupiter.params.shadow.de.siegmar.fastcsv.util",
      "org.junit.jupiter.params.shadow.de.siegmar.fastcsv.writer",
      "org.junit.jupiter.params.support"
    ],
    "org.junit.platform:junit-platform-commons": [
      "org.junit.platform.commons",
      "org.junit.platform.commons.annotation",
      "org.junit.platform.commons.function",
      "org.junit.platform.commons.io",
      "org.junit.platform.commons.logging",
      "org.junit.platform.commons.support",
      "org.junit.platform.commons.support.conversion",
      "org.junit.platform.commons.support.scanning",
      "org.junit.platform.commons.util"
    ],
    "org.junit.platform:junit-platform-console-standalone": [
      "junit.extensions",
      "junit.framework",
      "junit.runner",
      "junit.textui",
      "org.apiguardian.api",
      "org.hamcrest",
      "org.hamcrest.core",
      "org.hamcrest.internal",
      "org.junit",
      "org.junit.experimental",
      "org.junit.experimental.categories",
      "org.junit.experimental.max",
      "org.junit.experimental.results",
      "org.junit.experimental.runners",
      "org.junit.experimental.theories",
      "org.junit.experimental.theories.internal",
      "org.junit.experimental.theories.suppliers",
      "org.junit.function",
      "org.junit.internal",
      "org.junit.internal.builders",
      "org.junit.internal.management",
      "org.junit.internal.matchers",
      "org.junit.internal.requests",
      "org.junit.internal.runners",
      "org.junit.internal.runners.model",
      "org.junit.internal.runners.rules",
      "org.junit.internal.runners.statements",
      "org.junit.jupiter.api",
      "org.junit.jupiter.api.condition",
      "org.junit.jupiter.api.extension",
      "org.junit.jupiter.api.extension.support",
      "org.junit.jupiter.api.function",
      "org.junit.jupiter.api.io",
      "org.junit.jupiter.api.parallel",
      "org.junit.jupiter.api.util",
      "org.junit.jupiter.engine",
      "org.junit.jupiter.engine.config",
      "org.junit.jupiter.engine.descriptor",
      "org.junit.jupiter.engine.discovery",
      "org.junit.jupiter.engine.discovery.predicates",
      "org.junit.jupiter.engine.execution",
      "org.junit.jupiter.engine.extension",
      "org.junit.jupiter.engine.support",
      "org.junit.jupiter.params",
      "org.junit.jupiter.params.aggregator",
      "org.junit.jupiter.params.converter",
      "org.junit.jupiter.params.provider",
      "org.junit.jupiter.params.shadow.de.siegmar.fastcsv.reader",
      "org.junit.jupiter.params.shadow.de.siegmar.fastcsv.util",
      "org.junit.jupiter.params.shadow.de.siegmar.fastcsv.writer",
      "org.junit.jupiter.params.support",
      "org.junit.matchers",
      "org.junit.platform.commons",
      "org.junit.platform.commons.annotation",
      "org.junit.platform.commons.function",
      "org.junit.platform.commons.io",
      "org.junit.platform.commons.logging",
      "org.junit.platform.commons.support",
      "org.junit.platform.commons.support.conversion",
      "org.junit.platform.commons.support.scanning",
      "org.junit.platform.commons.util",
      "org.junit.platform.console",
      "org.junit.platform.console.command",
      "org.junit.platform.console.options",
      "org.junit.platform.console.output",
      "org.junit.platform.console.shadow.picocli",
      "org.junit.platform.engine",
      "org.junit.platform.engine.discovery",
      "org.junit.platform.engine.reporting",
      "org.junit.platform.engine.support.config",
      "org.junit.platform.engine.support.descriptor",
      "org.junit.platform.engine.support.discovery",
      "org.junit.platform.engine.support.hierarchical",
      "org.junit.platform.engine.support.store",
      "org.junit.platform.launcher",
      "org.junit.platform.launcher.core",
      "org.junit.platform.launcher.jfr",
      "org.junit.platform.launcher.listeners",
      "org.junit.platform.launcher.listeners.discovery",
      "org.junit.platform.launcher.listeners.session",
      "org.junit.platform.launcher.tagexpression",
      "org.junit.platform.reporting",
      "org.junit.platform.reporting.legacy",
      "org.junit.platform.reporting.legacy.xml",
      "org.junit.platform.reporting.open.xml",
      "org.junit.platform.reporting.shadow.org.opentest4j.reporting.events.api",
      "org.junit.platform.reporting.shadow.org.opentest4j.reporting.events.core",
      "org.junit.platform.reporting.shadow.org.opentest4j.reporting.events.git",
      "org.junit.platform.reporting.shadow.org.opentest4j.reporting.events.java",
      "org.junit.platform.reporting.shadow.org.opentest4j.reporting.events.root",
      "org.junit.platform.reporting.shadow.org.opentest4j.reporting.schema",
      "org.junit.platform.suite.api",
      "org.junit.platform.suite.engine",
      "org.junit.rules",
      "org.junit.runner",
      "org.junit.runner.manipulation",
      "org.junit.runner.notification",
      "org.junit.runners",
      "org.junit.runners.model",
      "org.junit.runners.parameterized",
      "org.junit.validator",
      "org.junit.vintage.engine",
      "org.junit.vintage.engine.descriptor",
      "org.junit.vintage.engine.discovery",
      "org.junit.vintage.engine.execution",
      "org.junit.vintage.engine.support",
      "org.opentest4j",
      "org.opentest4j.reporting.tooling.spi.htmlreport"
    ],
    "org.junit.platform:junit-platform-engine": [
      "org.junit.platform.engine",
      "org.junit.platform.engine.discovery",
      "org.junit.platform.engine.reporting",
      "org.junit.platform.engine.support.config",
      "org.junit.platform.engine.support.descriptor",
      "org.junit.platform.engine.support.discovery",
      "org.junit.platform.engine.support.hierarchical",
      "org.junit.platform.engine.support.store"
    ],
    "org.junit.platform:junit-platform-launcher": [
      "org.junit.platform.launcher",
      "org.junit.platform.launcher.core",
      "org.junit.platform.launcher.jfr",
      "org.junit.platform.launcher.listeners",
      "org.junit.platform.launcher.listeners.discovery",
      "org.junit.platform.launcher.listeners.session",
      "org.junit.platform.launcher.tagexpression"
    ],
    "org.opentest4j:opentest4j": [
      "org.opentest4j"
    ],
    "org.ow2.asm:asm": [
      "org.objectweb.asm",
      "org.objectweb.asm.signature"
    ],
    "org.ow2.asm:asm-analysis": [
      "org.objectweb.asm.tree.analysis"
    ],
    "org.ow2.asm:asm-commons": [
      "org.objectweb.asm.commons"
    ],
    "org.ow2.asm:asm-tree": [
      "org.objectweb.asm.tree"
    ],
    "org.ow2.asm:asm-util": [
      "org.objectweb.asm.util"
    ],
    "org.slf4j:slf4j-api": [
      "org.slf4j",
      "org.slf4j.event",
      "org.slf4j.helpers",
      "org.slf4j.spi"
    ],
    "org.wildfly.common:wildfly-common": [
      "org.wildfly.common",
      "org.wildfly.common._private",
      "org.wildfly.common.annotation",
      "org.wildfly.common.archive",
      "org.wildfly.common.array",
      "org.wildfly.common.bytes",
      "org.wildfly.common.codec",
      "org.wildfly.common.context",
      "org.wildfly.common.cpu",
      "org.wildfly.common.expression",
      "org.wildfly.common.flags",
      "org.wildfly.common.function",
      "org.wildfly.common.iteration",
      "org.wildfly.common.lock",
      "org.wildfly.common.math",
      "org.wildfly.common.net",
      "org.wildfly.common.os",
      "org.wildfly.common.ref",
      "org.wildfly.common.rpc",
      "org.wildfly.common.selector",
      "org.wildfly.common.string",
      "org.wildfly.common.xml"
    ]
  },
  "repositories": {
    "https://repo1.maven.org/maven2/": [
      "io.github.dmlloyd:jdk-classfile-backport",
      "io.quarkus.arc:arc",
      "io.quarkus.gizmo:gizmo",
      "io.quarkus.gizmo:gizmo2",
      "io.quarkus:quarkus-bootstrap-app-model",
      "io.quarkus:quarkus-bootstrap-core",
      "io.quarkus:quarkus-bootstrap-runner",
      "io.quarkus:quarkus-builder",
      "io.quarkus:quarkus-class-change-agent",
      "io.quarkus:quarkus-classloader-commons",
      "io.quarkus:quarkus-core",
      "io.quarkus:quarkus-core-deployment",
      "io.quarkus:quarkus-development-mode-spi",
      "io.quarkus:quarkus-fs-util",
      "io.quarkus:quarkus-hibernate-validator-spi",
      "io.quarkus:quarkus-ide-launcher",
      "io.smallrye.common:smallrye-common-annotation",
      "io.smallrye.common:smallrye-common-classloader",
      "io.smallrye.common:smallrye-common-constraint",
      "io.smallrye.common:smallrye-common-cpu",
      "io.smallrye.common:smallrye-common-expression",
      "io.smallrye.common:smallrye-common-function",
      "io.smallrye.common:smallrye-common-io",
      "io.smallrye.common:smallrye-common-net",
      "io.smallrye.common:smallrye-common-os",
      "io.smallrye.common:smallrye-common-process",
      "io.smallrye.common:smallrye-common-ref",
      "io.smallrye.common:smallrye-common-resource",
      "io.smallrye.config:smallrye-config",
      "io.smallrye.config:smallrye-config-common",
      "io.smallrye.config:smallrye-config-core",
      "io.smallrye.reactive:mutiny",
      "io.smallrye:jandex",
      "io.smallrye:jandex-gizmo2",
      "jakarta.annotation:jakarta.annotation-api",
      "jakarta.el:jakarta.el-api",
      "jakarta.enterprise:jakarta.enterprise.cdi-api",
      "jakarta.enterprise:jakarta.enterprise.lang-model",
      "jakarta.inject:jakarta.inject-api",
      "jakarta.interceptor:jakarta.interceptor-api",
      "jakarta.json:jakarta.json-api",
      "jakarta.transaction:jakarta.transaction-api",
      "org.aesh:aesh",
      "org.aesh:readline",
      "org.apache.commons:commons-lang3",
      "org.apiguardian:apiguardian-api",
      "org.crac:crac",
      "org.eclipse.microprofile.config:microprofile-config-api",
      "org.eclipse.parsson:parsson",
      "org.eclipse.sisu:org.eclipse.sisu.inject",
      "org.fusesource.jansi:jansi",
      "org.graalvm.sdk:nativeimage",
      "org.graalvm.sdk:word",
      "org.jboss.logging:commons-logging-jboss-logging",
      "org.jboss.logging:jboss-logging",
      "org.jboss.logmanager:jboss-logmanager",
      "org.jboss.slf4j:slf4j-jboss-logmanager",
      "org.jboss.threads:jboss-threads",
      "org.jctools:jctools-core",
      "org.jspecify:jspecify",
      "org.junit.jupiter:junit-jupiter",
      "org.junit.jupiter:junit-jupiter-api",
      "org.junit.jupiter:junit-jupiter-engine",
      "org.junit.jupiter:junit-jupiter-params",
      "org.junit.platform:junit-platform-commons",
      "org.junit.platform:junit-platform-console-standalone",
      "org.junit.platform:junit-platform-engine",
      "org.junit.platform:junit-platform-launcher",
      "org.opentest4j:opentest4j",
      "org.ow2.asm:asm",
      "org.ow2.asm:asm-analysis",
      "org.ow2.asm:asm-commons",
      "org.ow2.asm:asm-tree",
      "org.ow2.asm:asm-util",
      "org.slf4j:slf4j-api",
      "org.wildfly.common:wildfly-common"
    ]
  },
  "services": {
    "io.quarkus:quarkus-bootstrap-runner": {
      "org.jboss.logmanager.LogContextConfigurator": [
        "io.quarkus.bootstrap.logging.EmptyLogContextConfigurator"
      ],
      "org.jboss.logmanager.LogContextInitializer": [
        "io.quarkus.bootstrap.logging.InitialConfigurator"
      ]
    },
    "io.quarkus:quarkus-core": {
      "io.smallrye.config.SmallRyeConfigFactory": [
        "io.quarkus.runtime.configuration.QuarkusConfigFactory"
      ],
      "org.eclipse.microprofile.config.spi.Converter": [
        "io.quarkus.runtime.configuration.CharsetConverter",
        "io.quarkus.runtime.configuration.CidrAddressConverter",
        "io.quarkus.runtime.configuration.DurationConverter",
        "io.quarkus.runtime.configuration.InetAddressConverter",
        "io.quarkus.runtime.configuration.InetSocketAddressConverter",
        "io.quarkus.runtime.configuration.LocaleConverter",
        "io.quarkus.runtime.configuration.MemorySizeConverter",
        "io.quarkus.runtime.configuration.PathConverter",
        "io.quarkus.runtime.configuration.RegexConverter",
        "io.quarkus.runtime.configuration.ZoneIdConverter",
        "io.quarkus.runtime.logging.LevelConverter"
      ]
    },
    "io.quarkus:quarkus-core-deployment": {
      "io.quarkus.deployment.dev.CompilationProvider": [
        "io.quarkus.deployment.dev.JavaCompilationProvider"
      ],
      "io.smallrye.config.SmallRyeConfigBuilderCustomizer": [
        "io.quarkus.deployment.configuration.BuildTimeConfigBuilderCustomizer"
      ]
    },
    "io.smallrye.config:smallrye-config": {
      "jakarta.enterprise.inject.spi.Extension": [
        "io.smallrye.config.inject.ConfigExtension"
      ]
    },
    "io.smallrye.config:smallrye-config-core": {
      "io.smallrye.config.ConfigSourceFactory": [
        "io.smallrye.config.PropertiesLocationConfigSourceFactory"
      ],
      "org.eclipse.microprofile.config.spi.ConfigProviderResolver": [
        "io.smallrye.config.SmallRyeConfigProviderResolver"
      ]
    },
    "org.eclipse.parsson:parsson": {
      "jakarta.json.spi.JsonProvider": [
        "org.eclipse.parsson.JsonProviderImpl"
      ]
    },
    "org.graalvm.sdk:nativeimage": {
      "org.graalvm.nativeimage.Platform": [
        "org.graalvm.nativeimage.Platform$ANDROID_AARCH64",
        "org.graalvm.nativeimage.Platform$IOS_AARCH64",
        "org.graalvm.nativeimage.Platform$IOS_AMD64",
        "org.graalvm.nativeimage.Platform$LINUX_AARCH64",
        "org.graalvm.nativeimage.Platform$LINUX_AMD64",
        "org.graalvm.nativeimage.Platform$LINUX_RISCV64",
        "org.graalvm.nativeimage.Platform$MACOS_AARCH64",
        "org.graalvm.nativeimage.Platform$MACOS_AMD64",
        "org.graalvm.nativeimage.Platform$WINDOWS_AARCH64",
        "org.graalvm.nativeimage.Platform$WINDOWS_AMD64"
      ]
    },
    "org.jboss.logging:commons-logging-jboss-logging": {
      "org.apache.commons.logging.LogFactory": [
        "org.apache.commons.logging.impl.JBossLogFactory"
      ]
    },
    "org.jboss.logmanager:jboss-logmanager": {
      "java.lang.System$LoggerFinder": [
        "org.jboss.logmanager.JBossLoggerFinder"
      ],
      "java.util.logging.LogManager": [
        "org.jboss.logmanager.LogManager"
      ],
      "org.jboss.logmanager.ConfiguratorFactory": [
        "org.jboss.logmanager.configuration.DefaultConfiguratorFactory"
      ]
    },
    "org.jboss.slf4j:slf4j-jboss-logmanager": {
      "org.slf4j.spi.SLF4JServiceProvider": [
        "org.slf4j.impl.JBossSlf4jServiceProvider"
      ]
    },
    "org.junit.jupiter:junit-jupiter-engine": {
      "org.junit.platform.engine.TestEngine": [
        "org.junit.jupiter.engine.JupiterTestEngine"
      ]
    },
    "org.junit.platform:junit-platform-console-standalone": {
      "java.util.spi.ToolProvider": [
        "org.junit.platform.console.ConsoleLauncherToolProvider"
      ],
      "org.junit.platform.engine.TestEngine": [
        "org.junit.jupiter.engine.JupiterTestEngine",
        "org.junit.platform.suite.engine.SuiteTestEngine",
        "org.junit.vintage.engine.VintageTestEngine"
      ],
      "org.junit.platform.engine.discovery.DiscoverySelectorIdentifierParser": [
        "org.junit.platform.engine.discovery.ClassSelector$IdentifierParser",
        "org.junit.platform.engine.discovery.ClasspathResourceSelector$IdentifierParser",
        "org.junit.platform.engine.discovery.ClasspathRootSelector$IdentifierParser",
        "org.junit.platform.engine.discovery.DirectorySelector$IdentifierParser",
        "org.junit.platform.engine.discovery.FileSelector$IdentifierParser",
        "org.junit.platform.engine.discovery.IterationSelector$IdentifierParser",
        "org.junit.platform.engine.discovery.MethodSelector$IdentifierParser",
        "org.junit.platform.engine.discovery.ModuleSelector$IdentifierParser",
        "org.junit.platform.engine.discovery.NestedClassSelector$IdentifierParser",
        "org.junit.platform.engine.discovery.NestedMethodSelector$IdentifierParser",
        "org.junit.platform.engine.discovery.PackageSelector$IdentifierParser",
        "org.junit.platform.engine.discovery.UniqueIdSelector$IdentifierParser",
        "org.junit.platform.engine.discovery.UriSelector$IdentifierParser"
      ],
      "org.junit.platform.launcher.TestExecutionListener": [
        "org.junit.platform.launcher.listeners.UniqueIdTrackingListener",
        "org.junit.platform.reporting.open.xml.OpenTestReportGeneratingListener"
      ],
      "org.opentest4j.reporting.tooling.spi.htmlreport.Contributor": [
        "org.junit.platform.reporting.open.xml.JUnitContributor"
      ]
    },
    "org.junit.platform:junit-platform-engine": {
      "org.junit.platform.engine.discovery.DiscoverySelectorIdentifierParser": [
        "org.junit.platform.engine.discovery.ClassSelector$IdentifierParser",
        "org.junit.platform.engine.discovery.ClasspathResourceSelector$IdentifierParser",
        "org.junit.platform.engine.discovery.ClasspathRootSelector$IdentifierParser",
        "org.junit.platform.engine.discovery.DirectorySelector$IdentifierParser",
        "org.junit.platform.engine.discovery.FileSelector$IdentifierParser",
        "org.junit.platform.engine.discovery.IterationSelector$IdentifierParser",
        "org.junit.platform.engine.discovery.MethodSelector$IdentifierParser",
        "org.junit.platform.engine.discovery.ModuleSelector$IdentifierParser",
        "org.junit.platform.engine.discovery.NestedClassSelector$IdentifierParser",
        "org.junit.platform.engine.discovery.NestedMethodSelector$IdentifierParser",
        "org.junit.platform.engine.discovery.PackageSelector$IdentifierParser",
        "org.junit.platform.engine.discovery.UniqueIdSelector$IdentifierParser",
        "org.junit.platform.engine.discovery.UriSelector$IdentifierParser"
      ]
    },
    "org.junit.platform:junit-platform-launcher": {
      "org.junit.platform.launcher.TestExecutionListener": [
        "org.junit.platform.launcher.listeners.UniqueIdTrackingListener"
      ]
    }
  },
  "version": "3"
}
